topsis_Bhavya_102003409/__init__.py
topsis_Bhavya_102003409/topsis_Bhavya_102003409.py
topsis_Bhavya_102003409-0.0.1.dist-info/METADATA
topsis_Bhavya_102003409-0.0.1.dist-info/WHEEL
topsis_Bhavya_102003409-0.0.1.dist-info/top_level.txt
topsis_Bhavya_102003409-0.0.1.dist-info/RECORD
